microbit.py
microbit_dummy-0.0.1.dist-info/DESCRIPTION.rst
microbit_dummy-0.0.1.dist-info/METADATA
microbit_dummy-0.0.1.dist-info/RECORD
microbit_dummy-0.0.1.dist-info/WHEEL
microbit_dummy-0.0.1.dist-info/metadata.json
microbit_dummy-0.0.1.dist-info/top_level.txt
