Metadata-Version: 2.0
Name: microbit-dummy
Version: 0.0.1
Summary: A dummy Python implementation of the microbit module for MicroPython.
Home-page: https://github.com/hickford/microbit-dummy-python-api
Author: UNKNOWN
Author-email: UNKNOWN
License: MIT
Platform: UNKNOWN
Classifier: License :: OSI Approved :: MIT License
Classifier: Programming Language :: Python :: 2
Classifier: Programming Language :: Python :: 3
